streamlit_pydantic/__init__.py
streamlit_pydantic/_about.py
streamlit_pydantic/schema_utils.py
streamlit_pydantic/settings.py
streamlit_pydantic/types.py
streamlit_pydantic/ui_renderer.py
streamlit_pydantic-0.6.0.dist-info/LICENSE
streamlit_pydantic-0.6.0.dist-info/METADATA
streamlit_pydantic-0.6.0.dist-info/WHEEL
streamlit_pydantic-0.6.0.dist-info/top_level.txt
streamlit_pydantic-0.6.0.dist-info/RECORD
