Metadata-Version: 2.1
Name: streamlit-pydantic
Version: 0.6.0
Summary: Auto-generate Streamlit UI from Pydantic Models & Dataclasses.
Home-page: https://github.com/lukasmasuch/streamlit-pydantic
Author: Lukas Masuch
Author-email: lukas.masuch@gmail.com
License: MIT
Project-URL: Changelog, https://github.com/lukasmasuch/streamlit-pydantic/releases
Project-URL: Issue Tracker, https://github.com/lukasmasuch/streamlit-pydantic/issues
Project-URL: Documentation, https://github.com/lukasmasuch/streamlit-pydantic#documentation
Project-URL: Source, https://github.com/lukasmasuch/streamlit-pydantic
Classifier: Development Status :: 4 - Beta
Classifier: Intended Audience :: Developers
Classifier: Intended Audience :: Science/Research
Classifier: Intended Audience :: Information Technology
Classifier: License :: OSI Approved :: MIT License
Classifier: Natural Language :: English
Classifier: Operating System :: OS Independent
Classifier: Programming Language :: Python :: 3 :: Only
Classifier: Programming Language :: Python :: 3
Classifier: Programming Language :: Python :: 3.7
Classifier: Programming Language :: Python :: 3.8
Classifier: Programming Language :: Python :: 3.9
Classifier: Programming Language :: Python :: Implementation :: PyPy
Classifier: Programming Language :: Python :: Implementation :: CPython
Classifier: Topic :: Software Development
Classifier: Topic :: Software Development :: Libraries
Classifier: Topic :: Software Development :: Libraries :: Python Modules
Classifier: Topic :: Scientific/Engineering :: Artificial Intelligence
Classifier: Topic :: Scientific/Engineering
Classifier: Topic :: Utilities
Requires-Python: >=3.7
Provides-Extra: dev
License-File: LICENSE
